mappersession/__init__.py
mappersession/__main__.py
mappersession/mappersession.py
mappersession/mappingSessionSchema.json
mappersession/libmapper/__init__.py
mappersession/libmapper/libmapper.dylib
mappersession/libmapper/mapper.py
mappersession/libmapper/mapper.py.in
mappersession-0.0.16.dist-info/METADATA
mappersession-0.0.16.dist-info/WHEEL
mappersession-0.0.16.dist-info/licenses/LICENSE
mappersession-0.0.16.dist-info/RECORD
