Metadata-Version: 2.4
Name: mappersession
Version: 0.0.16
Summary: Session management tools in python for the libmapper signal mapping framework
Project-URL: Homepage, https://github.com/libmapper/mappersession
Project-URL: Bug Tracker, https://github.com/libmapper/mappersession/issues
Author-email: Brady Boettcher <bradyboettcher@gmail.com>, Joseph Malloch <joseph.malloch@gmail.com>
License-File: LICENSE
Classifier: License :: OSI Approved :: GNU Lesser General Public License v2 (LGPLv2)
Classifier: Operating System :: OS Independent
Classifier: Programming Language :: Python :: 3
Requires-Python: >=3.7
Requires-Dist: jsonschema
Requires-Dist: libmapper
